Wartungsplan.py
__init__.py
addEventToIcal.py
Wartungsplan-0.4.dist-info/LICENSE.txt
Wartungsplan-0.4.dist-info/METADATA
Wartungsplan-0.4.dist-info/WHEEL
Wartungsplan-0.4.dist-info/entry_points.txt
Wartungsplan-0.4.dist-info/top_level.txt
Wartungsplan-0.4.dist-info/RECORD
