Metadata-Version: 2.1
Name: Wartungsplan
Version: 0.4
Summary: Manage recurring tasks in ical
Author-email: Felix Bauer <felix.bauer@atos.net>
Maintainer-email: Felix Bauer <felix.bauer@eviden.com>, Christian Habrom <christian.habrom@eviden.com>
License: GPLv3
Project-URL: repository, https://github.com/science-computing/wartungsplan
Requires-Python: >=3.6
License-File: LICENSE.txt
Requires-Dist: icalendar ==5.0.10
Requires-Dist: python-dateutil ==2.8.2
Requires-Dist: recurring-ical-events ==2.1.0
Requires-Dist: Requests ==2.31.0
Requires-Dist: importlib-metadata ==6.8.0
Provides-Extra: otrs
Requires-Dist: pyotrs ==1.0.1 ; extra == 'otrs'
